metsrw/__init__.py
metsrw/di.py
metsrw/exceptions.py
metsrw/fsentry.py
metsrw/metadata.py
metsrw/mets.py
metsrw/utils.py
metsrw/validate.py
metsrw/plugins/__init__.py
metsrw/plugins/premisrw/__init__.py
metsrw/plugins/premisrw/premis.py
metsrw/plugins/premisrw/utils.py
metsrw/resources/archivematica_mets_pointer_file_schematron.xml
metsrw/resources/archivematica_mets_schematron.xml
metsrw/resources/mets.xsd
metsrw-0.6.1.dist-info/LICENSE
metsrw-0.6.1.dist-info/METADATA
metsrw-0.6.1.dist-info/WHEEL
metsrw-0.6.1.dist-info/top_level.txt
metsrw-0.6.1.dist-info/RECORD
