Metadata-Version: 2.2
Name: metsrw
Version: 0.6.1
Summary: Library for dealing with METS files.
Author-email: "Artefactual Systems Inc." <info@artefactual.com>
Maintainer-email: "Artefactual Systems Inc." <info@artefactual.com>
License:                     GNU AFFERO GENERAL PUBLIC LICENSE
Project-URL: homepage, https://github.com/artefactual-labs/mets-reader-writer/
Project-URL: documentation, https://mets-reader-writer.readthedocs.io/
Project-URL: repository, https://github.com/artefactual-labs/mets-reader-writer/
Project-URL: issues, https://github.com/archivematica/Issues/issues
Keywords: archivematica,preservation
Classifier: Development Status :: 3 - Alpha
Classifier: Environment :: Console
Classifier: Intended Audience :: Information Technology
Classifier: License :: OSI Approved :: GNU Affero General Public License v3
Classifier: Operating System :: POSIX :: Linux
Classifier: Programming Language :: Python :: 3 :: Only
Classifier: Programming Language :: Python :: 3.9
Classifier: Programming Language :: Python :: 3.10
Classifier: Programming Language :: Python :: 3.11
Classifier: Programming Language :: Python :: 3.12
Classifier: Programming Language :: Python :: 3.13
Requires-Python: >=3.9
License-File: LICENSE
Requires-Dist: lxml
Provides-Extra: dev
Requires-Dist: coverage; extra == "dev"
Requires-Dist: pip-tools; extra == "dev"
Requires-Dist: pytest-cov; extra == "dev"
Requires-Dist: pytest; extra == "dev"
Requires-Dist: ruff; extra == "dev"
Requires-Dist: sphinx-rtd-theme; extra == "dev"
Requires-Dist: sphinx; extra == "dev"
